acacia_s2s_toolkit/__init__.py
acacia_s2s_toolkit/argument_check.py
acacia_s2s_toolkit/argument_output.py
acacia_s2s_toolkit/download_forecast.py
acacia_s2s_toolkit/download_hindcast.py
acacia_s2s_toolkit/merge_lag_ensemble.py
acacia_s2s_toolkit/variable_dict.py
acacia_s2s_toolkit/webAPI_requests.py
acacia_s2s_toolkit/lookup_tables/__init__.py
acacia_s2s_toolkit/lookup_tables/lookup_table_20240514.csv
acacia_s2s_toolkit/lookup_tables/lookup_table_20240613.csv
acacia_s2s_toolkit/lookup_tables/lookup_table_20240821.csv
acacia_s2s_toolkit/lookup_tables/lookup_table_20241016.csv
acacia_s2s_toolkit/lookup_tables/lookup_table_20241112.csv
acacia_s2s_toolkit/lookup_tables/lookup_table_20241115.csv
acacia_s2s_toolkit-1.62.dist-info/licenses/LICENSE
acacia_s2s_toolkit-1.62.dist-info/METADATA
acacia_s2s_toolkit-1.62.dist-info/WHEEL
acacia_s2s_toolkit-1.62.dist-info/top_level.txt
acacia_s2s_toolkit-1.62.dist-info/RECORD
