Metadata-Version: 2.4
Name: acacia_s2s_toolkit
Version: 1.62
Summary: A python package to support download and analysis of forecasts from ECMWF S2S Database.
Author-email: Joshua Talib <joshuatalib@ecmwf.int>, Innocent Masukwedza <g.t.masukwedza@reading.ac.uk>
Project-URL: Homepage, https://github.com/joshuatalib/acacia_s2s_toolkit
Classifier: Programming Language :: Python :: 3
Classifier: License :: OSI Approved :: MIT License
Classifier: Operating System :: OS Independent
Requires-Python: >=3.8
License-File: LICENSE
Requires-Dist: numpy>=1.23
Requires-Dist: cdo>=1.6.0
Requires-Dist: xarray>=2024.9.0
Requires-Dist: eccodes>=2.40.0
Requires-Dist: dask>=2024.9.0
Requires-Dist: pandas>=2.2.3
Requires-Dist: scipy>=1.14.1
Requires-Dist: netCDF4>=1.7.2
Requires-Dist: requests>=2.32.2
Requires-Dist: matplotlib>=3.8
Requires-Dist: cartopy>=0.22
Dynamic: license-file
